pyactup.py
pyactup-2.2.4.dist-info/LICENSE
pyactup-2.2.4.dist-info/METADATA
pyactup-2.2.4.dist-info/WHEEL
pyactup-2.2.4.dist-info/top_level.txt
pyactup-2.2.4.dist-info/RECORD
