Metadata-Version: 2.1
Name: pyactup
Version: 2.2.4
Summary: A lightweight Python implementation of a subset of the ACT-R cognitive architecture’s Declarative Memory
Home-page: https://dfmorrison.github.io/pyactup-documentation/
Author: Don Morrison
Author-email: dfm2@cmu.edu
License: UNKNOWN
Platform: any
Classifier: Intended Audience :: Science/Research
Classifier: License :: OSI Approved :: MIT License
Classifier: Programming Language :: Python
Classifier: Programming Language :: Python :: 3 :: Only
Classifier: Programming Language :: Python :: 3.8
Classifier: Programming Language :: Python :: 3.9
Classifier: Programming Language :: Python :: 3.10
Classifier: Programming Language :: Python :: 3.11
Classifier: Operating System :: OS Independent
Requires-Python: >=3.8
License-File: LICENSE
Requires-Dist: numpy
Requires-Dist: pylru
Requires-Dist: prettytable
Requires-Dist: packaging
